qualityvision/BlurDetectorModule.py
qualityvision/FaceMeshModule.py
qualityvision/HandTrackingModule.py
qualityvision/__init__.py
qualityvision-0.1.2.dist-info/licenses/LICENSE.txt
qualityvision-0.1.2.dist-info/METADATA
qualityvision-0.1.2.dist-info/WHEEL
qualityvision-0.1.2.dist-info/top_level.txt
qualityvision-0.1.2.dist-info/RECORD
