Metadata-Version: 2.4
Name: qualityvision
Version: 0.1.2
Summary: A simple Blur Detection module using numpy and OpenCV
Home-page: https://github.com/ngrahulp/qualityvision
Author: Rahul Patekar
Author-email: ngrahulpatekar@gmail.com
Classifier: Programming Language :: Python :: 3
Classifier: License :: OSI Approved :: MIT License
Classifier: Operating System :: OS Independent
Requires-Python: >=3.7
License-File: LICENSE.txt
Requires-Dist: opencv-python>=4.5.0
Requires-Dist: numpy>=1.23.0
Requires-Dist: requests>=2.28.0
Requires-Dist: Pillow>=9.0.0
Dynamic: author
Dynamic: author-email
Dynamic: classifier
Dynamic: description
Dynamic: description-content-type
Dynamic: home-page
Dynamic: license-file
Dynamic: requires-dist
Dynamic: requires-python
Dynamic: summary
